Metadata-Version: 2.1
Name: pyqvrelite
Version: 0.0.1
Summary: QVR Pro/Elite API wrapper.
Home-page: https://github.com/trunet/pyqvrelite
Author: Wagner Sartori Junior
Author-email: wsartori@wsartori.com
License: MIT
Platform: UNKNOWN
Classifier: License :: OSI Approved :: MIT License
Classifier: Programming Language :: Python
Classifier: Programming Language :: Python :: 3
Classifier: Programming Language :: Python :: 3.8
Classifier: Programming Language :: Python :: Implementation :: CPython
Classifier: Programming Language :: Python :: Implementation :: PyPy
Requires-Python: >=3.8.0
